coloredtxt/__init__.py
coloredtxt/ansi.py
coloredtxt/ansitowin32.py
coloredtxt/initialise.py
coloredtxt/win32.py
coloredtxt/winterm.py
coloredtxt/libs/__init__.py
coloredtxt/libs/argparse.py
coloredtxt/libs/os.py
coloredtxt/libs/logging/__init__.py
coloredtxt/libs/logging/config.py
coloredtxt/libs/logging/handlers.py
coloredtxt/libs/requests/__init__.py
coloredtxt/libs/requests/__version__.py
coloredtxt/libs/requests/_internal_utils.py
coloredtxt/libs/requests/compat.py
coloredtxt/libs/requests/cookies.py
coloredtxt/libs/requests/exceptions.py
coloredtxt/libs/requests/help.py
coloredtxt/libs/requests/hooks.py
coloredtxt/libs/requests/models.py
coloredtxt/libs/requests/packages.py
coloredtxt/libs/requests/sessions.py
coloredtxt/libs/requests/status_codes.py
coloredtxt/libs/requests/structures.py
coloredtxt/libs/requests/utils.py
coloredtxt/tests/__init__.py
coloredtxt/tests/ansi_test.py
coloredtxt/tests/ansitowin32_test.py
coloredtxt/tests/initialise_test.py
coloredtxt/tests/isatty_test.py
coloredtxt/tests/utils.py
coloredtxt/tests/winterm_test.py
coloredtxt-0.0.2.dist-info/LICENSE.txt
coloredtxt-0.0.2.dist-info/METADATA
coloredtxt-0.0.2.dist-info/WHEEL
coloredtxt-0.0.2.dist-info/top_level.txt
coloredtxt-0.0.2.dist-info/RECORD
